data4ai/__init__.py
data4ai/__main__.py
data4ai/atomic_writer.py
data4ai/checkpoint.py
data4ai/cli.py
data4ai/cli_wrapper.py
data4ai/client.py
data4ai/config.py
data4ai/content_tracker.py
data4ai/deduplicator.py
data4ai/document_handler.py
data4ai/error_handler.py
data4ai/exceptions.py
data4ai/generator.py
data4ai/publisher.py
data4ai/py.typed
data4ai/rate_limiter.py
data4ai/schemas.py
data4ai/session_manager.py
data4ai/utils.py
data4ai/version_checker.py
data4ai/integrations/__init__.py
data4ai/integrations/dspy_document_prompts.py
data4ai/integrations/dspy_prompts.py
data4ai/integrations/openrouter_dspy.py
data4ai/integrations/youtube_handler.py
data4ai-0.3.0.dist-info/METADATA
data4ai-0.3.0.dist-info/WHEEL
data4ai-0.3.0.dist-info/entry_points.txt
data4ai-0.3.0.dist-info/licenses/LICENSE
data4ai-0.3.0.dist-info/RECORD
