Metadata-Version: 2.4
Name: data4ai
Version: 0.3.0
Summary: Production-ready AI-powered dataset generation for instruction tuning and model fine-tuning
Project-URL: Homepage, https://github.com/zysec-ai/data4ai
Project-URL: Documentation, https://github.com/zysec-ai/data4ai/blob/main/README.md
Project-URL: Repository, https://github.com/zysec-ai/data4ai
Project-URL: Issues, https://github.com/zysec-ai/data4ai/issues
Author-email: ZySec AI <support@zysec.ai>
License: MIT
License-File: LICENSE
Keywords: ai,dataset,instruction-tuning,llm,machine-learning,training-data
Classifier: Development Status :: 4 - Beta
Classifier: Intended Audience :: Developers
Classifier: Intended Audience :: Science/Research
Classifier: License :: OSI Approved :: MIT License
Classifier: Programming Language :: Python :: 3
Classifier: Programming Language :: Python :: 3.9
Classifier: Programming Language :: Python :: 3.10
Classifier: Programming Language :: Python :: 3.11
Classifier: Programming Language :: Python :: 3.12
Classifier: Topic :: Scientific/Engineering :: Artificial Intelligence
Requires-Python: >=3.9
Requires-Dist: build>=1.3.0
Requires-Dist: dspy-ai>=2.6.27
Requires-Dist: httpx<1.0.0,>=0.25.0
Requires-Dist: huggingface-hub<1.0.0,>=0.19.0
Requires-Dist: markdown<4.0.0,>=3.5.0
Requires-Dist: packaging<25.0,>=21.0
Requires-Dist: pandas<3.0.0,>=2.0.0
Requires-Dist: pdfplumber<1.0.0,>=0.10.0
Requires-Dist: pydantic-settings<3.0.0,>=2.0.0
Requires-Dist: pydantic<3.0.0,>=2.0.0
Requires-Dist: pypdf<5.0.0,>=3.17.0
Requires-Dist: python-docx<2.0.0,>=1.1.0
Requires-Dist: python-dotenv<2.0.0,>=1.0.0
Requires-Dist: pyyaml<7.0.0,>=6.0.0
Requires-Dist: ratelimit>=2.2.1
Requires-Dist: rich<14.0.0,>=13.0.0
Requires-Dist: tenacity<9.0.0,>=8.2.0
Requires-Dist: twine>=6.1.0
Requires-Dist: typer<1.0.0,>=0.9.0
Requires-Dist: yt-dlp>=2024.1.0
Provides-Extra: dev
Requires-Dist: black>=23.0.0; extra == 'dev'
Requires-Dist: mypy>=1.0.0; extra == 'dev'
Requires-Dist: pre-commit>=3.5.0; extra == 'dev'
Requires-Dist: pytest-asyncio>=0.21.0; extra == 'dev'
Requires-Dist: pytest-cov>=4.0.0; extra == 'dev'
Requires-Dist: pytest>=7.0.0; extra == 'dev'
Requires-Dist: ruff>=0.1.0; extra == 'dev'
Requires-Dist: types-pyyaml>=6.0.0; extra == 'dev'
Requires-Dist: types-requests>=2.31.0; extra == 'dev'
